[
    {
        "id": "486547",
        "title": "4G",
        "url": "https://en.wikipedia.org/?curid=486547",
        "header": [
            "",
            "LTE Advanced"
        ],
        "rows": [
            [
                "Peak download",
                "1000\u00a0Mbit/s"
            ],
            [
                "Peak upload",
                "500\u00a0Mbit/s"
            ]
        ],
        "column_types": [
            "string",
            "string"
        ],
        "key_column": 0,
        "numeric_columns": [],
        "date_columns": {},
        "qas": [
            {
                "source": "synthetic_qa",
                "question": "How many  had LTE Advanced string contains 500?",
                "answers": [
                    "1"
                ],
                "reasoning_type": "counting"
            },
            {
                "source": "synthetic_qa",
                "question": "How many  had LTE Advanced string starts with 500?",
                "answers": [
                    "1"
                ],
                "reasoning_type": "counting"
            }
        ]
    },
    {
        "id": "486547",
        "title": "4G",
        "url": "https://en.wikipedia.org/?curid=486547",
        "header": [
            "",
            "LTE"
        ],
        "rows": [
            [
                "Peak download",
                "150\u00a0Mbit/s"
            ],
            [
                "Peak upload",
                "50\u00a0Mbit/s"
            ]
        ],
        "column_types": [
            "string",
            "string"
        ],
        "key_column": 0,
        "numeric_columns": [],
        "date_columns": {},
        "qas": [
            {
                "source": "synthetic_qa",
                "question": "How many  had LTE string contains 50?",
                "answers": [
                    "2"
                ],
                "reasoning_type": "counting"
            },
            {
                "source": "synthetic_qa",
                "question": "How many  had LTE string starts with 50?",
                "answers": [
                    "1"
                ],
                "reasoning_type": "counting"
            }
        ]
    },
    {
        "id": "486547",
        "title": "4G",
        "url": "https://en.wikipedia.org/?curid=486547",
        "header": [
            "",
            "WiMAX"
        ],
        "rows": [
            [
                "Peak download",
                "128\u00a0Mbit/s"
            ],
            [
                "Peak upload",
                "56\u00a0Mbit/s"
            ]
        ],
        "column_types": [
            "string",
            "string"
        ],
        "key_column": 0,
        "numeric_columns": [],
        "date_columns": {},
        "qas": [
            {
                "source": "synthetic_qa",
                "question": "How many  had WiMAX string starts with 56?",
                "answers": [
                    "1"
                ],
                "reasoning_type": "counting"
            }
        ]
    },
    {
        "id": "486547",
        "title": "4G",
        "url": "https://en.wikipedia.org/?curid=486547",
        "header": [
            "Country",
            "Network",
            "Shutdown date",
            "Standard",
            "Notes"
        ],
        "rows": [
            [
                "",
                "Xplore Mobile",
                "2022-08-31",
                "LTE",
                ""
            ],
            [
                "",
                "Digicel",
                "2018-10-31",
                "WiMAX",
                ""
            ],
            [
                "",
                "Yes 4G",
                "2019-10-01",
                "WiMAX",
                ""
            ],
            [
                "",
                "Nepal Telecom",
                "",
                "WiMAX",
                ""
            ],
            [
                "",
                "Blink bmobile (TSTT)",
                "2015-03-03",
                "WiMAX",
                ""
            ],
            [
                "",
                "Sprint",
                "2016-03-31",
                "WiMAX",
                ""
            ],
            [
                "",
                "T-Mobile (Sprint)",
                "2022-06-30",
                "LTE",
                ""
            ]
        ],
        "column_types": [
            "string",
            "string"
        ],
        "key_column": 0,
        "numeric_columns": [],
        "date_columns": {},
        "qas": []
    }
]