[
    {
        "id": "9440913",
        "title": "Sandrine Rousseau",
        "url": "https://fr.wikipedia.org/?curid=9440913",
        "header": [
            "Ann\u00e9e",
            "Parti",
            "Parti",
            "",
            "",
            "",
            "",
            "",
            "",
            "Issue"
        ],
        "rows": [
            [
                "Ann\u00e9e",
                "Parti",
                "Parti",
                "Voix",
                "%",
                "Rang",
                "Voix",
                "%",
                "Rang",
                "Issue"
            ],
            [
                "2021",
                "",
                "E\u00c9LV",
                "",
                "25,14",
                "",
                "",
                "48,97",
                "",
                "Battue"
            ]
        ],
        "column_types": [
            "UNKNOWN",
            "UNKNOWN",
            "UNKNOWN",
            "ORG",
            "CARDINAL",
            "UNKNOWN",
            "ORG",
            "CARDINAL",
            "UNKNOWN",
            "UNKNOWN"
        ],
        "key_column": 2,
        "numeric_columns": [],
        "date_columns": {}
    },
    {
        "id": "9440913",
        "title": "Sandrine Rousseau",
        "url": "https://fr.wikipedia.org/?curid=9440913",
        "header": [
            "Ann\u00e9e",
            "Parti",
            "Parti",
            "Circonscription",
            "",
            "",
            "",
            "",
            "Issue"
        ],
        "rows": [
            [
                "Ann\u00e9e",
                "Parti",
                "Parti",
                "Circonscription",
                "%",
                "Rang",
                "%",
                "Rang",
                "Issue"
            ],
            [
                ".",
                "",
                "E\u00c9LV",
                "du Nord",
                "16,71",
                "",
                "",
                "",
                "\u00c9limin\u00e9e"
            ],
            [
                ".",
                "",
                "E\u00c9LV",
                "du Nord",
                "4,74",
                "",
                "",
                "",
                "\u00c9limin\u00e9e"
            ],
            [
                "",
                "",
                "E\u00c9LV (NUPES)",
                "de Paris",
                "42,90",
                "",
                "58,05",
                "",
                "\u00c9lue"
            ]
        ],
        "column_types": [
            "UNKNOWN",
            "UNKNOWN",
            "UNKNOWN",
            "UNKNOWN",
            "CARDINAL",
            "UNKNOWN",
            "CARDINAL",
            "UNKNOWN",
            "UNKNOWN"
        ],
        "key_column": 2,
        "numeric_columns": [],
        "date_columns": {}
    },
    {
        "id": "9440913",
        "title": "Sandrine Rousseau",
        "url": "https://fr.wikipedia.org/?curid=9440913",
        "header": [
            "Ann\u00e9e",
            "Parti",
            "Parti",
            "Bin\u00f4me",
            "Canton",
            "",
            "",
            "Issue"
        ],
        "rows": [
            [
                "Ann\u00e9e",
                "Parti",
                "Parti",
                "Bin\u00f4me",
                "Canton",
                "%",
                "Rang",
                "Issue"
            ],
            [
                ".",
                "",
                "E\u00c9LV",
                "H\u00e9l\u00e8ne Hardy(E\u00c9LV)",
                "Villeneuve-d'Ascq",
                "8,84",
                "",
                "\u00c9limin\u00e9e"
            ]
        ],
        "column_types": [
            "UNKNOWN",
            "UNKNOWN",
            "UNKNOWN",
            "PERSON",
            "GPE",
            "CARDINAL",
            "UNKNOWN",
            "UNKNOWN"
        ],
        "key_column": 2,
        "numeric_columns": [],
        "date_columns": {}
    },
    {
        "id": "9440913",
        "title": "Sandrine Rousseau",
        "url": "https://fr.wikipedia.org/?curid=9440913",
        "header": [
            "Ann\u00e9e",
            "Liste",
            "Liste",
            "R\u00e9gion",
            "",
            "",
            "Si\u00e8ges obtenus"
        ],
        "rows": [
            [
                "Ann\u00e9e",
                "Liste",
                "Liste",
                "R\u00e9gion",
                "%",
                "Rang",
                "Si\u00e8ges obtenus"
            ],
            [
                ".",
                "",
                "E\u00c9LV-PG-ND",
                "Hauts-de-France",
                "4,83",
                "",
                ""
            ]
        ],
        "column_types": [
            "UNKNOWN",
            "UNKNOWN",
            "UNKNOWN",
            "UNKNOWN",
            "CARDINAL",
            "UNKNOWN",
            "UNKNOWN"
        ],
        "key_column": 2,
        "numeric_columns": [],
        "date_columns": {}
    },
    {
        "id": "9440913",
        "title": "Sandrine Rousseau",
        "url": "https://fr.wikipedia.org/?curid=9440913",
        "header": [
            "Ann\u00e9e",
            "Liste",
            "Liste",
            "Commune",
            "",
            "",
            "Si\u00e8ges obtenus",
            "Si\u00e8ges obtenus"
        ],
        "rows": [
            [
                "Ann\u00e9e",
                "Liste",
                "Liste",
                "Commune",
                "%",
                "Rang",
                "",
                "MEL"
            ],
            [
                ".",
                "",
                "E\u00c9LV",
                "Villeneuve-d'Ascq",
                "9,94",
                "",
                "",
                ""
            ]
        ],
        "column_types": [
            "UNKNOWN",
            "UNKNOWN",
            "UNKNOWN",
            "ORG",
            "CARDINAL",
            "UNKNOWN",
            NaN,
            "PERSON"
        ],
        "key_column": 2,
        "numeric_columns": [],
        "date_columns": {}
    }
]