[
    {
        "id": "397301",
        "title": "3GPP",
        "url": "https://en.wikipedia.org/?curid=397301",
        "header": [
            "Organization",
            "Country/region",
            "Website"
        ],
        "rows": [
            [
                "Association of Radio Industries and Businesses (ARIB)",
                "Japan",
                "ARIB"
            ],
            [
                "Alliance for Telecommunications Industry Solutions (ATIS)",
                "USA",
                "ATIS"
            ],
            [
                "China Communications Standards Association (CCSA)",
                "China",
                "CCSA"
            ],
            [
                "European Telecommunications Standards Institute (ETSI)",
                "Europe",
                "ETSI"
            ],
            [
                "Telecommunications Standards Development Society (TSDSI)",
                "India",
                "TSDSI"
            ],
            [
                "Telecommunications Technology Association (TTA)",
                "South Korea",
                "TTA"
            ],
            [
                "Telecommunication Technology Committee (TTC)",
                "Japan",
                "TTC"
            ]
        ],
        "column_types": [
            "string",
            "string",
            "string"
        ],
        "key_column": 0,
        "numeric_columns": [],
        "date_columns": {}
    },
    {
        "id": "397301",
        "title": "3GPP",
        "url": "https://en.wikipedia.org/?curid=397301",
        "header": [
            "Organization",
            "Website"
        ],
        "rows": [
            [
                "5G-ACIA",
                "http://www.5g-acia.org"
            ],
            [
                "5G Automotive Association",
                "http://www.5gaa.org/"
            ],
            [
                "5G Americas",
                "http://www.5gamericas.org"
            ],
            [
                "5G Deterministic Networking Alliance (5GDNA)",
                "https://www.5gdna.org/"
            ],
            [
                "5G Infrastructure Association",
                "https://5g-ppp.eu/association/"
            ],
            [
                "5G Media Action Group (5G-MAG)",
                "http://www.5g-mag.com/"
            ],
            [
                "Automotive Edge Computing Consortium (AECC)",
                "https://aecc.org/"
            ],
            [
                "Broadband India Forum",
                "http://www.broadbandindiaforum.com/"
            ],
            [
                "Cellular Operators Association of India (COAI)",
                "https://www.coai.com"
            ],
            [
                "China Society of Automotive Engineers (CSAE)",
                "http://www.sae-china.org/"
            ],
            [
                "CTIA",
                "http://ctia.org/"
            ],
            [
                "EMEA Satellite Operators Association (ESOA)",
                "https://www.esoa.net/"
            ],
            [
                "Global Certification Forum (GCF)",
                "https://www.globalcertificationforum.org/"
            ],
            [
                "Global mobile Suppliers Association (GSA)",
                "https://gsacom.com/"
            ],
            [
                "GSMA",
                "https://www.gsma.com/"
            ],
            [
                "IPV6 Forum",
                "https://www.ipv6forum.com/"
            ],
            [
                "Next Generation Mobile Networks (NGMN)",
                "https://www.ngmn.org/"
            ],
            [
                "Public Safety Communication Europe (PSCE) Forum",
                "http://www.psc-europe.eu/"
            ],
            [
                "Small Cell Forum",
                "https://www.smallcellforum.org/"
            ],
            [
                "TCCA",
                "https://tcca.info/"
            ],
            [
                "TD Industry Alliance",
                "http://www.tdia.cn/"
            ],
            [
                "Wireless Broadband Alliance",
                "http://www.wballiance.com/"
            ]
        ],
        "column_types": [
            "string",
            "string"
        ],
        "key_column": 0,
        "numeric_columns": [],
        "date_columns": {}
    },
    {
        "id": "397301",
        "title": "3GPP",
        "url": "https://en.wikipedia.org/?curid=397301",
        "header": [
            "VersionReleases",
            "Released",
            "Info"
        ],
        "rows": [
            [
                "Phase 1",
                "1992",
                "GSM Features"
            ],
            [
                "Phase 2",
                "1995",
                "GSM Features, EFR Codec,"
            ],
            [
                "Release 96",
                "1997 Q1",
                "GSM Features, 14.4 kbit/s User Data Rate,"
            ],
            [
                "Release 97",
                "1998 Q1",
                "GSM Features, GPRS"
            ],
            [
                "Release 98",
                "1999 Q1",
                "GSM Features, AMR codec, EDGE, GPRS for PCS1900"
            ],
            [
                "Release 99",
                "2000 Q1",
                "Specified the first UMTS 3G networks, incorporating a CDMA air interfaceOverview of 3GPP Release 99, Summary of all Release 99 Features. ETSI Mobile Competence Centre, Version xx/07/04"
            ],
            [
                "Release 4",
                "2001 Q2",
                "Originally called the Release 2000 – added features including an all-IP Core NetworkOverview of 3GPP Release 4, Summary of all Release 4 Features, v.1.1.0 (draft) ETSI Mobile Competence Centre 2004"
            ],
            [
                "Release 5",
                "2002 Q1",
                "Introduced IMS and HSDPASummary of all Release 5 Features, ETSI Mobile Competence Centre, Version 9 September 2003"
            ],
            [
                "Release 6",
                "2004 Q4",
                "Integrated operation with Wireless LAN networks and adds HSUPA, MBMS, enhancements to IMS such as Push to Talk over Cellular (PoC), GANOverview of 3GPP Release 6, Summary of all Release 6 Features, Version TSG #33, ETSI Mobile Competence Centre 2006"
            ],
            [
                "Release 7",
                "2007 Q4",
                "Focuses on decreasing latency, improvements to QoS and real-time applications such as VoIP.Review of the Work Plan at Plenaries #31, 3GPP, SP-060232 3GPP TSG SA#31 Sanya, 13–16 March 2006 This specification also focus on HSPA+ (High Speed Packet Access Evolution), SIM high-speed protocol and contactless front-end interface (Near Field Communication enabling operators to deliver contactless services like Mobile Payments), EDGE Evolution."
            ],
            [
                "Release 8",
                "2008 Q4",
                "First LTE release. All-IP Network (SAE). New OFDMA, FDE and MIMO based radio interface, not backwards compatible with previous CDMA interfaces. Dual-Cell HSDPA. UMTS HNB."
            ],
            [
                "Release 9",
                "2009 Q4",
                "SAES Enhancements, WiMAX and LTE/UMTS Interoperability. Dual-Cell HSDPA with MIMO, Dual-Cell HSUPA. LTE HeNB. Evolved multimedia broadcast and multicast service (eMBMS)."
            ],
            [
                "Release 10",
                "2011 Q1",
                "LTE Advanced fulfilling IMT Advanced 4G requirements. Backwards compatible with release 8 (LTE). Multi-Cell HSDPA (4 carriers)."
            ],
            [
                "Release 11",
                "2012 Q3",
                "Advanced IP Interconnection of Services. Service layer interconnection between national operators/carriers as well as third-party application providers. Heterogeneous networks (HetNet) improvements, Coordinated Multi-Point operation (CoMP). In-device Co-existence (IDC)."
            ],
            [
                "Release 12",
                "2015 Q1",
                "Enhanced Small Cells (higher order modulation, dual connectivity, cell discovery, self configuration), Carrier aggregation (2 uplink carriers, 3 downlink carriers, FDD/TDD carrier aggregation), MIMO (3D channel modeling, elevation beamforming, massive MIMO), New and Enhanced Services (cost and range of MTC, D2D communication, eMBMS enhancements)"
            ],
            [
                "Release 13",
                "2016 Q1",
                "LTE-Advanced Pro. LTE in unlicensed, LTE enhancements for Machine-Type Communication. Elevation Beamforming / Full-Dimension MIMO, Indoor positioning."
            ],
            [
                "Release 14",
                "2017 Q2",
                "Energy Efficiency, Location Services (LCS), Mission Critical Data over LTE, Mission Critical Video over LTE, Flexible Mobile Service Steering (FMSS), Multimedia Broadcast Supplement for Public Warning System (MBSP), enhancement for TV services over eMBMS, massive Internet of Things, Cell Broadcast Service (CBS)"
            ],
            [
                "Release 15",
                "2018 Q2",
                "First 5G NR (\"New Radio\") release. Support for 5G Vehicle-to-x service, IP Multimedia Core Network Subsystem (IMS), Future Railway Mobile Communication System"
            ],
            [
                "Release 16",
                "2020 Q3",
                "The 5G System – Phase 2: 5G enhancements, NR-based access to unlicensed spectrum (NR-U), Satellite access"
            ],
            [
                "Release 17",
                "2022 Q1",
                "TSG RAN: Several features that continue to be important for overall efficiency and performance of 5G NR: MIMO, Spectrum Sharing enhancements, UE Power Saving and Coverage Enhancements. RAN1 will also undertake the necessary study and specification work to enhance the physical layer to support frequency bands up to 71 GHz.\n\nTSG SA groups focused on further enhancements to the 5G system and enablers for new features and services:\n\nEnhanced support of: non-public networks, industrial Internet of Things, low complexity NR devices, edge computing in 5GC, access traffic steering, switch and splitting support, network automation for 5G, network slicing, advanced V2X service, multiple USIM support, proximity-based services in 5GS, 5G multicast broadcast services, Unmanned Aerial Systems (UAS), satellite access in 5G, 5GC location services, Multimedia Priority Service..."
            ],
            [
                "Release 18",
                "2023 Q4",
                "5G-Advanced. Introducing further machine-learning based techniques at different levels of the wireless network. Edge computing, Evolution of IMS Multimedia Telephony Service, Smart Energy and Infrastructure, Vehicle-Mounted Relays, Low Power High Accuracy Positioning for industrial IoT scenarios, Enhanced Access to and Support of Network slicing, Satellite backhaul in 5G..."
            ]
        ],
        "column_types": [
            "string",
            "string",
            "string"
        ],
        "key_column": 0,
        "numeric_columns": [],
        "date_columns": {}
    },
    {
        "id": "397301",
        "title": "3GPP",
        "url": "https://en.wikipedia.org/?curid=397301",
        "header": [
            "WG",
            "Shorthand",
            "Scope",
            "Specifications"
        ],
        "rows": [
            [
                "RAN WG1",
                "RAN1",
                "Radio Layer 1 (Physical layer)",
                "List of specs"
            ],
            [
                "RAN WG2",
                "RAN2",
                "Radio Layer 2 and Radio Layer 3 Radio Resource Control",
                "List of specs"
            ],
            [
                "RAN WG3",
                "RAN3",
                "UTRAN, E-UTRAN, NG-RAN architecture and related network interfaces",
                "List of specs"
            ],
            [
                "RAN WG4",
                "RAN4",
                "Radio performance and protocol aspects",
                "List of specs"
            ],
            [
                "RAN WG5",
                "RAN5",
                "Mobile terminal conformance testing",
                "List of specs"
            ]
        ],
        "column_types": [
            "string",
            "string",
            "string",
            "string"
        ],
        "key_column": 0,
        "numeric_columns": [],
        "date_columns": {}
    },
    {
        "id": "397301",
        "title": "3GPP",
        "url": "https://en.wikipedia.org/?curid=397301",
        "header": [
            "WG",
            "Shorthand",
            "Scope",
            "Specifications"
        ],
        "rows": [
            [
                "SA WG1",
                "SA1",
                "Services",
                "List of specs"
            ],
            [
                "SA WG2",
                "SA2",
                "Architecture",
                "List of specs"
            ],
            [
                "SA WG3",
                "SA3",
                "Security",
                "List of specs"
            ],
            [
                "SA WG4",
                "SA4",
                "Codec",
                "List of specs"
            ],
            [
                "SA WG5",
                "SA5",
                "Management, Orchestration and Charging",
                "List of specs"
            ],
            [
                "SA WG6",
                "SA6",
                "Application Enablement and Critical Communication Applications",
                "List of specs"
            ]
        ],
        "column_types": [
            "string",
            "string",
            "string",
            "string"
        ],
        "key_column": 0,
        "numeric_columns": [],
        "date_columns": {}
    },
    {
        "id": "397301",
        "title": "3GPP",
        "url": "https://en.wikipedia.org/?curid=397301",
        "header": [
            "WG",
            "Shorthand",
            "Scope",
            "Specifications"
        ],
        "rows": [
            [
                "CT WG1",
                "CT1",
                "User Equipment – Core Network protocols",
                "List of specs"
            ],
            [
                "CT WG2",
                "CT2",
                "closed",
                ""
            ],
            [
                "CT WG3",
                "CT3",
                "Interworking with external networks",
                "List of specs"
            ],
            [
                "CT WG4",
                "CT4",
                "Core Network Protocols",
                "List of specs"
            ],
            [
                "CT WG5",
                "CT5",
                "closed",
                ""
            ],
            [
                "CT WG6",
                "CT6",
                "Smart Card Application Aspects",
                "List of specs"
            ]
        ],
        "column_types": [
            "string",
            "string",
            "string",
            "string"
        ],
        "key_column": 0,
        "numeric_columns": [],
        "date_columns": {}
    }
]