[
    {
        "id": "141876",
        "title": "MyTravel Group",
        "url": "https://en.wikipedia.org/?curid=141876",
        "header": [
            "Name",
            "Country",
            "Fate"
        ],
        "rows": [
            [
                "MyTravel Tour Operations Limited",
                "United Kingdom",
                "Merged into Thomas Cook Tour Operations"
            ],
            [
                "Panorama Holiday Group Limited",
                "United Kingdom",
                "Transferred to Thomas Cook Group (2007)\nDissolution (2014)"
            ],
            [
                "BCT Travel Group Limited",
                "United Kingdom",
                "Transferred to Thomas Cook Group (2007)\nRebranded to Thomas Cook Scheduled Tour Operations Limited (2008)\n\nDissolution (2015)"
            ],
            [
                "Direct Holidays plc",
                "United Kingdom",
                "Dissolution (2013)"
            ],
            [
                "Tj\u00e6reborg",
                "DenmarkFinland",
                "Transferred to Thomas Cook Group (2007)"
            ],
            [
                "Spies",
                "Denmark",
                "Transferred to Thomas Cook Group (2007)"
            ],
            [
                "Ving",
                "DenmarkNorwaySweden",
                "Transferred to Thomas Cook Group (2007)"
            ],
            [
                "ALBA Tours",
                "Canada",
                "Transferred to Thomas Cook Group (2007)"
            ],
            [
                "Sunquest Vacations",
                "Canada",
                "Transferred to Thomas Cook Group (2007)\nSold to Red Label Vacations (2013)"
            ]
        ],
        "column_types": [
            "string",
            "string",
            "string"
        ],
        "key_column": 0,
        "numeric_columns": [],
        "date_columns": {},
        "qas": [
            {
                "source": "synthetic_qa",
                "question": "What was the Name when the Country string contains Kingdom and the Fate string starts with Dissolution?",
                "answers": [
                    "Direct Holidays plc"
                ],
                "reasoning_type": "conjunction"
            },
            {
                "source": "synthetic_qa",
                "question": "What was the Name when the Country is Canada and the Fate string starts with Transferred?",
                "answers": [
                    "ALBA Tours",
                    "Sunquest Vacations"
                ],
                "reasoning_type": "conjunction"
            },
            {
                "source": "synthetic_qa",
                "question": "Does every Name, with Fate string starts with Transferred, have Country is Canada?",
                "answers": [
                    "No"
                ],
                "reasoning_type": "quantifiers"
            },
            {
                "source": "synthetic_qa",
                "question": "Does only Name, with Fate string starts with Transferred, have Country string starts with United?",
                "answers": [
                    "No"
                ],
                "reasoning_type": "quantifiers"
            },
            {
                "source": "synthetic_qa",
                "question": "How many Name had Fate string starts with Transferred?",
                "answers": [
                    "7"
                ],
                "reasoning_type": "counting"
            },
            {
                "source": "synthetic_qa",
                "question": "How many Name had Fate string contains Group and Country is Canada?",
                "answers": [
                    "2"
                ],
                "reasoning_type": "counting"
            },
            {
                "source": "synthetic_qa",
                "question": "How many Name had Fate string contains Cook and Country string starts with United?",
                "answers": [
                    "3"
                ],
                "reasoning_type": "counting"
            }
        ]
    },
    {
        "id": "141876",
        "title": "MyTravel Group",
        "url": "https://en.wikipedia.org/?curid=141876",
        "header": [
            "Airline",
            "Country",
            "Image",
            "Description",
            "Fate"
        ],
        "rows": [
            [
                "MyTravel Airways Limited",
                "United Kingdom",
                "125x125px",
                "MyTravel Airways Limited was a British scheduled and charter airline, formerly known as Airtours International.",
                "Transferred to Thomas Cook Group (2007) Merged with Thomas Cook Airlines UK (2008)"
            ],
            [
                "MyTravel Airways A/S",
                "Denmark",
                "124x124px",
                "MyTravel Airways was a Scandinavian scheduled and charter airline.",
                "Transferred to Thomas Cook Group (2007)\nRebranded to Thomas Cook Airlines Scandinavia (2008)"
            ]
        ],
        "column_types": [
            "string",
            "string",
            "string",
            "string",
            "string"
        ],
        "key_column": 0,
        "numeric_columns": [],
        "date_columns": {},
        "qas": [
            {
                "source": "synthetic_qa",
                "question": "What was the Airline when the Fate string contains UK and the Country string starts with United?",
                "answers": [
                    "MyTravel Airways Limited"
                ],
                "reasoning_type": "conjunction"
            },
            {
                "source": "synthetic_qa",
                "question": "What was the Airline when the Description string contains British and the Fate string contains UK?",
                "answers": [
                    "MyTravel Airways Limited"
                ],
                "reasoning_type": "conjunction"
            },
            {
                "source": "synthetic_qa",
                "question": "Does every Airline, with Fate string contains Cook, have Description string contains a?",
                "answers": [
                    "Yes"
                ],
                "reasoning_type": "quantifiers"
            },
            {
                "source": "synthetic_qa",
                "question": "Does every Airline, with Country string starts with United, have Description string contains scheduled?",
                "answers": [
                    "Yes"
                ],
                "reasoning_type": "quantifiers"
            },
            {
                "source": "synthetic_qa",
                "question": "How many Airline had Fate string starts with Transferred?",
                "answers": [
                    "2"
                ],
                "reasoning_type": "counting"
            },
            {
                "source": "synthetic_qa",
                "question": "How many Airline had Fate string contains Cook?",
                "answers": [
                    "2"
                ],
                "reasoning_type": "counting"
            }
        ]
    }
]