[
    {
        "id": "5581115",
        "title": "Eugenie Bouchard",
        "url": "https://fr.wikipedia.org/?curid=5581115",
        "header": [
            "#",
            "Date",
            "Nom de l'édition",
            "($)",
            "Surface",
            "Résultat",
            "Ultime adversaire",
            "class=unsortableScore",
            "class=unsortable"
        ],
        "rows": [
            [
                "!# !Date !Nom de l'édition !($) !Surface !Résultat !Ultime adversaire ! class=unsortableScore ! class=unsortable"
            ],
            [
                "1 20/10/2014",
                "''WTA Finals'' Singapour",
                "Dur ()",
                "Round Robin (défaite)",
                "Simona Halep",
                "6-2, 6-3Parcours"
            ],
            [
                "Round Robin (défaite)",
                "Ana Ivanović",
                "6-1, 6-3"
            ],
            [
                "Round Robin (défaite)",
                "Serena Williams",
                "6-1, 6-1"
            ]
        ],
        "column_types": [
            "string",
            "string",
            "string",
            "string",
            "string",
            "string",
            "numeric",
            "numeric",
            "numeric"
        ],
        "key_column": 6,
        "numeric_columns": [
            6,
            7,
            8
        ],
        "date_columns": {}
    }
]